8bit_music_lib-0.2.1.dist-info/licenses/LICENSE
music8bit/__init__.py
music8bit/mixer.py
music8bit/notes.py
music8bit/part.py
music8bit/utils.py
music8bit/wave.py
8bit_music_lib-0.2.1.dist-info/METADATA
8bit_music_lib-0.2.1.dist-info/WHEEL
8bit_music_lib-0.2.1.dist-info/top_level.txt
8bit_music_lib-0.2.1.dist-info/RECORD
