Metadata-Version: 2.4
Name: 8bit-music-lib
Version: 0.2.1
Summary: A simple 8bit-style music library
Home-page: https://github.com/neutrino-dot/8bit-music-lib
Author: neutrino-dot
License: MIT
Project-URL: Bug Tracker, https://github.com/neutrino-dot/8bit-music-lib/issues
Project-URL: Documentation, https://github.com/neutrino-dot/8bit-music-lib#readme
Project-URL: Source Code, https://github.com/neutrino-dot/8bit-music-lib
Project-URL: Release Notes, https://github.com/neutrino-dot/8bit-music-lib/releases
Classifier: Programming Language :: Python :: 3
Classifier: License :: OSI Approved :: MIT License
Classifier: Operating System :: OS Independent
Classifier: Development Status :: 3 - Alpha
Classifier: Intended Audience :: Developers
Classifier: Topic :: Multimedia :: Sound/Audio :: Sound Synthesis
Requires-Python: >=3.8
License-File: LICENSE
Requires-Dist: numpy
Requires-Dist: scipy
Provides-Extra: sounddevice
Requires-Dist: sounddevice; extra == "sounddevice"
Provides-Extra: simpleaudio
Requires-Dist: simpleaudio; extra == "simpleaudio"
Provides-Extra: jupyter
Requires-Dist: ipython; extra == "jupyter"
Dynamic: author
Dynamic: classifier
Dynamic: description
Dynamic: description-content-type
Dynamic: home-page
Dynamic: license
Dynamic: license-file
Dynamic: project-url
Dynamic: provides-extra
Dynamic: requires-dist
Dynamic: requires-python
Dynamic: summary
